qir_qis/py.typed
qir_qis/qir_qis.pyd
qir_qis/__init__.py
qir_qis/__init__.pyi
qir_qis-0.1.1.dist-info/DELVEWHEEL
qir_qis-0.1.1.dist-info/METADATA
qir_qis-0.1.1.dist-info/RECORD
qir_qis-0.1.1.dist-info/WHEEL
qir_qis-0.1.1.dist-info/licenses/LICENSE
qir_qis.libs/msvcp140-a4c2229bdc2a2a630acdc095b4d86008.dll
