Metadata-Version: 2.4
Name: qir_qis
Version: 0.1.1
Classifier: Programming Language :: Rust
Classifier: Programming Language :: Python :: Implementation :: CPython
Classifier: Programming Language :: Python :: Implementation :: PyPy
Classifier: Development Status :: 4 - Beta
Classifier: Intended Audience :: Developers
Classifier: Intended Audience :: Science/Research
Classifier: Topic :: Scientific/Engineering
Classifier: Topic :: Software Development :: Compilers
Classifier: License :: OSI Approved :: Apache Software License
License-File: LICENSE
Summary: QIR to Quantinuum QIS (Quantum Instruction Set) compiler
Home-Page: https://github.com/quantinuum/qir-qis
Author-email: Kartik Singhal <kartik.singhal@quantinuum.com>
Requires-Python: >=3.10, <3.15
Project-URL: repository, https://github.com/quantinuum/qir-qis/
